{
    "id": "-1",
    "name": "Organization Directory",
    "jevisclass": "Organization Directory",
    "attributes": [],
    "children": [
        {
            "id": "-3",
            "name": "Desigo",
            "jevisclass": "Organization"
        },
        {
            "name": "Desigo",
            "jevisclass": "Organization",
            "attributes": [
                {
                    "name": "Address",
                    "lastvalue": "Some Random Adress"
                },
                {
                    "name": "Members",
                    "lastvalue": "Me"
                }
            ],
            "children": [
                {
                    "name": "Monitored Object Directory",
                    "jevisclass": "Monitored Object Directory",
                    "attributes": [],
                    "children": [
                        {
                            "name": "Building",
                            "jevisclass": "Building",
                            "attributes": [],
                            "children": [
                                {
                                    "name": "Data Directory",
                                    "jevisclass": "Data Directory",
                                    "attributes": [],
                                    "children": [
                                        {
                                            "id": "1",
                                            "name": "WP-42 W채rmemenge Verbraucher",
                                            "jevisclass": "Data"
                                        },
                                        {
                                            "id": "2",
                                            "name": "WP-34 Stromverbrauch Pumpen f체r WMP1+2",
                                            "jevisclass": "Data"
                                        },
                                        {
                                            "id": "3",
                                            "name": "WS-10 Aussentemperatur",
                                            "jevisclass": "Data"
                                        }
                                    ]
                                },
                                {
                                    "name": "Data Source Directory",
                                    "jevisclass": "Data Source Directory",
                                    "attributes": [],
                                    "children": [
                                        {
                                            "name": "Desigo",
                                            "jevisclass": "MSSQL Server",
                                            "attributes": [
                                                {
                                                    "name": "Host",
                                                    "lastvalue": "localhost"
                                                },
                                                {
                                                    "name": "Port",
                                                    "lastvalue": "1433"
                                                },
                                                {
                                                    "name": "Schema",
                                                    "lastvalue": "PDM_DATA"
                                                },
                                                {
                                                    "name": "Domain",
                                                    "lastvalue": "IE10WIN7"
                                                },
                                                {
                                                    "name": "User",
                                                    "lastvalue": ""
                                                },
                                                {
                                                    "name": "Password",
                                                    "lastvalue": ""
                                                },
                                                {
                                                    "name": "Enabled",
                                                    "lastvalue": "true"
                                                }
                                            ],
                                            "children": [
                                                {
                                                    "name": "SQL Channel Directory",
                                                    "jevisclass": "SQL Channel Directory",
                                                    "attributes": [],
                                                    "children": [
                                                        {
                                                            "name": "SQL Channel",
                                                            "jevisclass": "SQL Channel",
                                                            "attributes": [
                                                                {
                                                                    "name": "Table",
                                                                    "lastvalue": "dbo.Value"
                                                                },
                                                                {
                                                                    "name": "Column ID",
                                                                    "lastvalue": "NamedItem_ID"
                                                                },
                                                                {
                                                                    "name": "Column Value",
                                                                    "lastvalue": "Value"
                                                                },
                                                                {
                                                                    "name": "Column Timestamp",
                                                                    "lastvalue": "RecTime"
                                                                },
                                                                {
                                                                    "name": "Timestamp Format",
                                                                    "lastvalue": "yyyy-MM-dd HH:mm:ss.s"
                                                                }
                                                            ],
                                                            "children": [
                                                                {
                                                                    "name": "SQL Data Point Directory",
                                                                    "jevisclass": "SQL Data Point Directory",
                                                                    "attributes": [],
                                                                    "children": [
                                                                        {
                                                                            "name": "WP-42 W채rmemenge Verbraucher",
                                                                            "jevisclass": "SQL Data Point",
                                                                            "attributes": [
                                                                                {
                                                                                    "name": "ID",
                                                                                    "lastvalue": "3"
                                                                                },
                                                                                {
                                                                                    "name": "Target",
                                                                                    "lastvalue": "$(REF)1"
                                                                                }
                                                                            ],
                                                                            "children": []
                                                                        },
                                                                        {
                                                                            "name": "WP-34 Stromverbrauch Pumpen f체r WMP1+2",
                                                                            "jevisclass": "SQL Data Point",
                                                                            "attributes": [
                                                                                {
                                                                                    "name": "ID",
                                                                                    "lastvalue": "9"
                                                                                },
                                                                                {
                                                                                    "name": "Target",
                                                                                    "lastvalue": "$(REF)2"
                                                                                }
                                                                            ],
                                                                            "children": []
                                                                        },
                                                                        {
                                                                            "name": "WS-10 Aussentemperatur",
                                                                            "jevisclass": "SQL Data Point",
                                                                            "attributes": [
                                                                                {
                                                                                    "name": "ID",
                                                                                    "lastvalue": "2229"
                                                                                },
                                                                                {
                                                                                    "name": "Target",
                                                                                    "lastvalue": "$(REF)3"
                                                                                }
                                                                            ],
                                                                            "children": []
                                                                        }
                                                                    ]
                                                                }
                                                            ]
                                                        }
                                                    ]
                                                }
                                            ]
                                        }
                                    ]
                                }
                            ]
                        }
                    ]
                }
            ]
        }
    ]
}
